[
  { "model": "partos.tipodeingreso", "pk": 1, "fields": { "nombre": "Parto espont치neo" } },
  { "model": "partos.tipodeingreso", "pk": 2, "fields": { "nombre": "Ces치rea programada" } },
  { "model": "partos.tipodeingreso", "pk": 3, "fields": { "nombre": "Ces치rea de urgencia" } },
  { "model": "partos.tipodeingreso", "pk": 4, "fields": { "nombre": "Remisi칩n desde otro centro de salud" } },
  { "model": "partos.tipodeingreso", "pk": 5, "fields": { "nombre": "Consulta externa/parto domiciliario trasladado" } }
]
